echopylang/__init__.py
echopylang/echomath.py
echopylang/echoprint.py
echopylang/echovar.py
echopylang-1.10.0.dist-info/METADATA
echopylang-1.10.0.dist-info/WHEEL
echopylang-1.10.0.dist-info/top_level.txt
echopylang-1.10.0.dist-info/RECORD
